serviceit/__init__.py
serviceit/server.py
serviceit-0.2.0.dist-info/LICENSE.txt
serviceit-0.2.0.dist-info/WHEEL
serviceit-0.2.0.dist-info/METADATA
serviceit-0.2.0.dist-info/RECORD
