Metadata-Version: 2.1
Name: serviceit
Version: 0.2.0
Summary: Turn any Python function into a service that receives JSON payloads on some port.
Home-page: https://github.com/dmyersturnbull/service-it
License: Apache-2.0
Keywords: socket,json,service,server
Author: Douglas Myers-Turnbull
Maintainer: Douglas Myers-Turnbull
Requires-Python: >=3.8,<4
Classifier: Development Status :: 4 - Beta
Classifier: Intended Audience :: Developers
Classifier: License :: OSI Approved :: Apache Software License
Classifier: Natural Language :: English
Classifier: Operating System :: OS Independent
Classifier: Programming Language :: Python :: 3
Classifier: Programming Language :: Python :: 3 :: Only
Classifier: Programming Language :: Python :: 3.8
Classifier: Programming Language :: Python :: 3.9
Classifier: Topic :: Software Development :: Libraries :: Python Modules
Provides-Extra: dev
Requires-Dist: tomlkit (>=0.7,<1.0)
Requires-Dist: typer (>=0.3,<1.0)
Project-URL: CI, https://github.com/dmyersturnbull/service-it/actions
Project-URL: Documentation, https://service-it.readthedocs.io
Project-URL: Download, https://pypi.org/project/serviceit/
Project-URL: Issues, https://github.com/dmyersturnbull/service-it/issues
Project-URL: Repository, https://github.com/dmyersturnbull/service-it
